{
    "2106D": {
        "success": false,
        "error": "No recent submissions found"
    },
    "2074E": {
        "success": false,
        "error": "No recent submissions found"
    },
    "2134C": {
        "success": true,
        "runId": 63429354
    },
    "2134A": {
        "success": true,
        "runId": 63429359
    },
    "2085A": {
        "success": false,
        "error": "No recent submissions found"
    },
    "2086A": {
        "success": false,
        "error": "No recent submissions found"
    },
    "2118D2": {
        "success": false,
        "error": "No recent submissions found"
    },
    "2094G": {
        "success": false,
        "error": "No recent submissions found"
    },
    "2136A": {
        "success": true,
        "runId": 63429384
    },
    "2120B": {
        "success": false,
        "error": "No recent submissions found"
    },
    "4A": {
        "success": false,
        "error": "No recent submissions found"
    },
    "2091E": {
        "success": false,
        "error": "No recent submissions found"
    },
    "2132A": {
        "success": true,
        "runId": 63429409
    },
    "2118E": {
        "success": true,
        "runId": 63429414
    },
    "2111B": {
        "success": false,
        "error": "No recent submissions found"
    },
    "2074C": {
        "success": false,
        "error": "No recent submissions found"
    },
    "2074G": {
        "success": false,
        "error": "No recent submissions found"
    },
    "2074B": {
        "success": false,
        "error": "No recent submissions found"
    },
    "2116C": {
        "success": false,
        "error": "No recent submissions found"
    },
    "2117C": {
        "success": false,
        "error": "No recent submissions found"
    },
    "50A": {
        "success": false,
        "error": "No recent submissions found"
    },
    "2094H": {
        "success": false,
        "error": "No recent submissions found"
    },
    "2117D": {
        "success": false,
        "error": "No recent submissions found"
    },
    "2090A": {
        "success": false,
        "error": "No recent submissions found"
    },
    "2108F": {
        "success": false,
        "error": "No recent submissions found"
    },
    "1385E": {
        "success": true,
        "runId": 63429442
    },
    "2114D": {
        "success": false,
        "error": "No recent submissions found"
    },
    "2091D": {
        "success": false,
        "error": "No recent submissions found"
    },
    "2136C": {
        "success": true,
        "runId": 63429455
    },
    "2086D": {
        "success": false,
        "error": "No recent submissions found"
    },
    "2131B": {
        "success": true,
        "runId": 63429461
    },
    "2128E2": {
        "success": false,
        "error": "No recent submissions found"
    },
    "2106C": {
        "success": false,
        "error": "No recent submissions found"
    },
    "2128D": {
        "success": false,
        "error": "No recent submissions found"
    },
    "282A": {
        "success": false,
        "error": "No recent submissions found"
    },
    "2128C": {
        "success": false,
        "error": "No recent submissions found"
    },
    "772A": {
        "success": false,
        "error": "No recent submissions found"
    },
    "231A": {
        "success": false,
        "error": "No recent submissions found"
    },
    "2114B": {
        "success": false,
        "error": "No recent submissions found"
    },
    "2120C": {
        "success": false,
        "error": "No recent submissions found"
    },
    "2007B": {
        "success": false,
        "error": "No recent submissions found"
    },
    "2117B": {
        "success": false,
        "error": "No recent submissions found"
    },
    "2128B": {
        "success": false,
        "error": "No recent submissions found"
    },
    "2085D": {
        "success": false,
        "error": "No recent submissions found"
    },
    "2085C": {
        "success": false,
        "error": "No recent submissions found"
    },
    "2134B": {
        "success": true,
        "runId": 63429505
    },
    "2126E": {
        "success": false,
        "error": "No recent submissions found"
    },
    "2075A": {
        "success": false,
        "error": "No recent submissions found"
    },
    "1245D": {
        "success": true,
        "runId": 63429516
    },
    "2074D": {
        "success": false,
        "error": "No recent submissions found"
    },
    "2090C": {
        "success": false,
        "error": "No recent submissions found"
    },
    "2128E1": {
        "success": false,
        "error": "No recent submissions found"
    },
    "2132E": {
        "success": true,
        "runId": 63429529
    },
    "807A": {
        "success": false,
        "error": "No recent submissions found"
    },
    "899C": {
        "success": false,
        "error": "No recent submissions found"
    },
    "2074F": {
        "success": false,
        "error": "No recent submissions found"
    },
    "2075B": {
        "success": false,
        "error": "No recent submissions found"
    },
    "1446A": {
        "success": true,
        "runId": 63429544
    },
    "2116B": {
        "success": false,
        "error": "No recent submissions found"
    },
    "731D": {
        "success": true,
        "runId": 63429555
    },
    "87C": {
        "success": true,
        "runId": 63429558
    },
    "901A": {
        "success": true,
        "runId": 63429569
    },
    "2122A": {
        "success": true,
        "runId": 63429571
    },
    "2111D": {
        "success": false,
        "error": "No recent submissions found"
    },
    "1807C": {
        "success": false,
        "error": "No recent submissions found"
    },
    "2106A": {
        "success": false,
        "error": "No recent submissions found"
    },
    "2133B": {
        "success": true,
        "runId": 63429592
    },
    "2094B": {
        "success": false,
        "error": "No recent submissions found"
    },
    "2118C": {
        "success": false,
        "error": "No recent submissions found"
    },
    "2119A": {
        "success": false,
        "error": "No recent submissions found"
    },
    "2094A": {
        "success": false,
        "error": "No recent submissions found"
    },
    "2128A": {
        "success": false,
        "error": "No recent submissions found"
    },
    "1144F": {
        "success": true,
        "runId": 63429615
    },
    "2074A": {
        "success": false,
        "error": "No recent submissions found"
    },
    "2091B": {
        "success": false,
        "error": "No recent submissions found"
    },
    "2119B": {
        "success": false,
        "error": "No recent submissions found"
    },
    "1120D": {
        "success": true,
        "runId": 63429627
    },
    "2116D": {
        "success": false,
        "error": "No recent submissions found"
    },
    "2106E": {
        "success": false,
        "error": "No recent submissions found"
    },
    "2131A": {
        "success": true,
        "runId": 63429634
    },
    "2091F": {
        "success": false,
        "error": "No recent submissions found"
    },
    "2117F": {
        "success": true,
        "runId": 63429640
    },
    "2106B": {
        "success": false,
        "error": "No recent submissions found"
    },
    "2117E": {
        "success": false,
        "error": "No recent submissions found"
    },
    "158A": {
        "success": false,
        "error": "No recent submissions found"
    },
    "2085B": {
        "success": false,
        "error": "No recent submissions found"
    },
    "2114E": {
        "success": false,
        "error": "No recent submissions found"
    },
    "2094E": {
        "success": false,
        "error": "No recent submissions found"
    },
    "2116A": {
        "success": false,
        "error": "No recent submissions found"
    },
    "2132F": {
        "success": true,
        "runId": 63429672
    },
    "2106F": {
        "success": false,
        "error": "No recent submissions found"
    },
    "2119C": {
        "success": false,
        "error": "No recent submissions found"
    },
    "888G": {
        "success": true,
        "runId": 63429678
    },
    "2094F": {
        "success": false,
        "error": "No recent submissions found"
    },
    "2133C": {
        "success": true,
        "runId": 63429681
    },
    "451B": {
        "success": false,
        "error": "No recent submissions found"
    },
    "2114A": {
        "success": false,
        "error": "No recent submissions found"
    },
    "2136B": {
        "success": true,
        "runId": 63429687
    },
    "2111C": {
        "success": false,
        "error": "No recent submissions found"
    },
    "2122C": {
        "success": false,
        "error": "No recent submissions found"
    },
    "2130A": {
        "success": true,
        "runId": 63429697
    },
    "2111A": {
        "success": false,
        "error": "No recent submissions found"
    },
    "2126A": {
        "success": true,
        "runId": 63429708
    },
    "2086C": {
        "success": true,
        "runId": 63429716
    },
    "2118A": {
        "success": false,
        "error": "No recent submissions found"
    },
    "1000E": {
        "success": true,
        "runId": 63429724
    },
    "2075D": {
        "success": false,
        "error": "No recent submissions found"
    },
    "2136D": {
        "success": true,
        "runId": 63429733
    },
    "2122D": {
        "success": false,
        "error": "No recent submissions found"
    },
    "2114C": {
        "success": false,
        "error": "No recent submissions found"
    },
    "2086B": {
        "success": false,
        "error": "No recent submissions found"
    },
    "2090B": {
        "success": false,
        "error": "No recent submissions found"
    },
    "3C": {
        "success": true,
        "runId": 63429742
    },
    "2117G": {
        "success": false,
        "error": "No recent submissions found"
    },
    "2091A": {
        "success": false,
        "error": "No recent submissions found"
    },
    "2120E": {
        "success": false,
        "error": "No recent submissions found"
    },
    "81C": {
        "success": true,
        "runId": 63429761
    },
    "2111E": {
        "success": false,
        "error": "No recent submissions found"
    },
    "2118B": {
        "success": false,
        "error": "No recent submissions found"
    },
    "263A": {
        "success": false,
        "error": "No recent submissions found"
    },
    "2117A": {
        "success": false,
        "error": "No recent submissions found"
    },
    "2122B": {
        "success": false,
        "error": "No recent submissions found"
    },
    "2136E": {
        "success": true,
        "runId": 63429784
    },
    "1063A": {
        "success": false,
        "error": "No recent submissions found"
    },
    "2094C": {
        "success": false,
        "error": "No recent submissions found"
    },
    "2075C": {
        "success": false,
        "error": "No recent submissions found"
    },
    "2091C": {
        "success": false,
        "error": "No recent submissions found"
    },
    "2118D1": {
        "success": false,
        "error": "No recent submissions found"
    },
    "2133A": {
        "success": true,
        "runId": 63429801
    },
    "2120A": {
        "success": false,
        "error": "No recent submissions found"
    },
    "173B": {
        "success": true,
        "runId": 63429808
    },
    "2090D": {
        "success": false,
        "error": "No recent submissions found"
    },
    "2091G": {
        "success": false,
        "error": "No recent submissions found"
    },
    "2094D": {
        "success": false,
        "error": "No recent submissions found"
    },
    "2134D": {
        "success": true,
        "runId": 63429817
    },
    "71A": {
        "success": false,
        "error": "No recent submissions found"
    },
    "2133D": {
        "success": true,
        "runId": 63429827
    },
    "141E": {
        "success": true,
        "runId": 63434930
    },
    "207A2": {
        "success": false,
        "error": "No recent submissions found"
    },
    "670E": {
        "success": false,
        "error": "No recent submissions found"
    },
    "2139E1": {
        "success": false,
        "error": "No recent submissions found"
    },
    "207A1": {
        "success": false,
        "error": "No recent submissions found"
    },
    "2137A": {
        "success": true,
        "runId": 63552879
    },
    "141D": {
        "success": false,
        "error": "No recent submissions found"
    },
    "2139B": {
        "success": false,
        "error": "No recent submissions found"
    },
    "2140D": {
        "success": false,
        "error": "No recent submissions found"
    },
    "2137C": {
        "success": false,
        "error": "No recent submissions found"
    },
    "2140C": {
        "success": true,
        "runId": 63552906
    },
    "2137B": {
        "success": true,
        "runId": 63552908
    },
    "2139D": {
        "success": false,
        "error": "No recent submissions found"
    },
    "2139E2": {
        "success": false,
        "error": "No recent submissions found"
    },
    "2139A": {
        "success": false,
        "error": "No recent submissions found"
    },
    "207A3": {
        "success": true,
        "runId": 63552926
    },
    "1207C": {
        "success": false,
        "error": "No recent submissions found"
    },
    "2137D": {
        "success": true,
        "runId": 63552935
    },
    "2140B": {
        "success": false,
        "error": "No recent submissions found"
    },
    "2139C": {
        "success": false,
        "error": "No recent submissions found"
    },
    "2140A": {
        "success": false,
        "error": "No recent submissions found"
    },
    "100384H": {
        "success": false,
        "error": "No recent submissions found"
    },
    "100008D": {
        "success": false,
        "error": "No recent submissions found"
    },
    "2144C": {
        "success": true,
        "runId": 63673175
    },
    "102861K": {
        "success": false,
        "error": "No recent submissions found"
    },
    "2144B": {
        "success": true,
        "runId": 63673176
    },
    "2144A": {
        "success": true,
        "runId": 63673177
    },
    "2148G": {
        "success": true,
        "runId": 63673182
    },
    "2148E": {
        "success": true,
        "runId": 63673183
    },
    "102861I": {
        "success": false,
        "error": "No recent submissions found"
    },
    "2148C": {
        "success": true,
        "runId": 63673185
    },
    "102791J": {
        "success": false,
        "error": "No recent submissions found"
    },
    "2148D": {
        "success": true,
        "runId": 63673187
    },
    "101466E": {
        "success": false,
        "error": "No recent submissions found"
    },
    "2148A": {
        "success": true,
        "runId": 63673191
    },
    "2148F": {
        "success": true,
        "runId": 63673193
    },
    "2148B": {
        "success": true,
        "runId": 63673195
    },
    "2144D": {
        "success": true,
        "runId": 63673197
    },
    "2143B": {
        "success": true,
        "runId": 63809135
    },
    "2143C": {
        "success": true,
        "runId": 63809136
    },
    "2127A": {
        "success": true,
        "runId": 63809141
    },
    "2147A": {
        "success": true,
        "runId": 63809145
    },
    "2147B": {
        "success": true,
        "runId": 63809148
    },
    "2143D1": {
        "success": true,
        "runId": 63809152
    },
    "2143A": {
        "success": true,
        "runId": 63809157
    },
    "2147D": {
        "success": true,
        "runId": 63809163
    },
    "2143E": {
        "success": true,
        "runId": 63809170
    },
    "2147C": {
        "success": true,
        "runId": 63809172
    },
    "2143D2": {
        "success": true,
        "runId": 63809176
    },
    "105851C": {
        "success": true,
        "runId": 63809376
    },
    "105851E": {
        "success": true,
        "runId": 63809379
    },
    "105459G": {
        "success": true,
        "runId": 63809387
    },
    "104805K": {
        "success": true,
        "runId": 63809389
    },
    "104059J": {
        "success": true,
        "runId": 63809393
    },
    "105493C": {
        "success": true,
        "runId": 63809400
    },
    "105884C": {
        "success": true,
        "runId": 63809407
    },
    "103114G": {
        "success": true,
        "runId": 63809409
    },
    "105459K": {
        "success": true,
        "runId": 63809419
    },
    "106068H": {
        "success": true,
        "runId": 63809420
    },
    "104182C": {
        "success": true,
        "runId": 63809424
    },
    "105819D": {
        "success": true,
        "runId": 63809429
    },
    "105562M": {
        "success": true,
        "runId": 63809435
    },
    "105946A": {
        "success": true,
        "runId": 63809440
    },
    "101875A": {
        "success": true,
        "runId": 63809443
    },
    "104030F": {
        "success": true,
        "runId": 63809465
    },
    "105459C": {
        "success": true,
        "runId": 63809470
    },
    "105459J": {
        "success": true,
        "runId": 63809478
    },
    "104772D": {
        "success": true,
        "runId": 63809486
    },
    "103114H": {
        "success": true,
        "runId": 63809488
    },
    "105851A": {
        "success": true,
        "runId": 63809490
    },
    "101875G": {
        "success": true,
        "runId": 63809492
    },
    "105459M": {
        "success": true,
        "runId": 63809495
    },
    "105862H": {
        "success": true,
        "runId": 63809499
    },
    "105484B": {
        "success": true,
        "runId": 63915581
    },
    "2146A": {
        "success": false,
        "error": "No recent submissions found"
    },
    "2125A": {
        "success": true,
        "runId": 63915585
    },
    "2151B": {
        "success": true,
        "runId": 63915589
    },
    "2146D2": {
        "success": true,
        "runId": 63915590
    },
    "2126B": {
        "success": true,
        "runId": 63915592
    },
    "105484J": {
        "success": true,
        "runId": 63915603
    },
    "2151A": {
        "success": true,
        "runId": 63915606
    },
    "2146B": {
        "success": true,
        "runId": 63915609
    },
    "2146C": {
        "success": true,
        "runId": 63915612
    },
    "105484E": {
        "success": true,
        "runId": 63915615
    },
    "105484K": {
        "success": true,
        "runId": 63915616
    },
    "2151C": {
        "success": true,
        "runId": 63915618
    },
    "2146D1": {
        "success": false,
        "error": "No recent submissions found"
    },
    "2155D": {
        "success": true,
        "runId": 64279356
    },
    "105588C": {
        "success": true,
        "runId": 64279362
    },
    "105588G": {
        "success": true,
        "runId": 64279368
    },
    "105588M": {
        "success": true,
        "runId": 64279376
    },
    "100488B": {
        "success": true,
        "runId": 64279384
    },
    "2149A": {
        "success": true,
        "runId": 64279391
    },
    "105578J": {
        "success": true,
        "runId": 64279394
    },
    "105578B": {
        "success": true,
        "runId": 64279398
    },
    "105578M": {
        "success": true,
        "runId": 64279400
    },
    "100488K": {
        "success": true,
        "runId": 64279403
    },
    "104777N": {
        "success": true,
        "runId": 64279407
    },
    "2155C": {
        "success": true,
        "runId": 64279411
    },
    "105486G": {
        "success": true,
        "runId": 64279419
    },
    "105486I": {
        "success": true,
        "runId": 64279424
    },
    "2152D": {
        "success": true,
        "runId": 64279428
    },
    "2152B": {
        "success": true,
        "runId": 64279432
    },
    "104822I": {
        "success": true,
        "runId": 64279437
    },
    "105657A": {
        "success": true,
        "runId": 64279444
    },
    "105657E": {
        "success": true,
        "runId": 64279447
    },
    "105657K": {
        "success": true,
        "runId": 64279449
    },
    "105578G": {
        "success": true,
        "runId": 64279476
    },
    "106032J": {
        "success": true,
        "runId": 64279486
    },
    "105486J": {
        "success": true,
        "runId": 64279488
    },
    "106042D": {
        "success": true,
        "runId": 64279492
    },
    "2152A": {
        "success": true,
        "runId": 64279497
    },
    "100488L": {
        "success": true,
        "runId": 64279501
    },
    "2149C": {
        "success": true,
        "runId": 64279507
    },
    "105053D": {
        "success": true,
        "runId": 64279514
    },
    "105394D": {
        "success": true,
        "runId": 64279520
    },
    "2145C": {
        "success": true,
        "runId": 64279529
    },
    "104790K": {
        "success": true,
        "runId": 64279545
    },
    "2155B": {
        "success": true,
        "runId": 64279548
    },
    "2137E": {
        "success": true,
        "runId": 64279555
    },
    "105387G": {
        "success": true,
        "runId": 64279561
    },
    "105578D": {
        "success": true,
        "runId": 64279570
    },
    "105588J": {
        "success": true,
        "runId": 64279574
    },
    "105578I": {
        "success": true,
        "runId": 64279578
    },
    "2145B": {
        "success": true,
        "runId": 64279583
    },
    "105486L": {
        "success": true,
        "runId": 64279587
    },
    "105486A": {
        "success": true,
        "runId": 64279592
    },
    "2145A": {
        "success": true,
        "runId": 64279611
    },
    "105588E": {
        "success": true,
        "runId": 64279617
    },
    "105657H": {
        "success": true,
        "runId": 64279618
    },
    "105431D": {
        "success": true,
        "runId": 64279623
    },
    "2149E": {
        "success": true,
        "runId": 64279634
    },
    "2149B": {
        "success": true,
        "runId": 64279636
    },
    "105822C": {
        "success": true,
        "runId": 64279639
    },
    "105552D": {
        "success": true,
        "runId": 64279645
    },
    "2152C": {
        "success": true,
        "runId": 64279649
    },
    "2149F": {
        "success": true,
        "runId": 64279651
    },
    "105588H": {
        "success": true,
        "runId": 64279656
    },
    "2014A": {
        "success": true,
        "runId": 64279660
    },
    "105578E": {
        "success": true,
        "runId": 64279665
    },
    "2149D": {
        "success": true,
        "runId": 64279668
    },
    "2155A": {
        "success": true,
        "runId": 64279671
    },
    "2145E": {
        "success": true,
        "runId": 64279677
    },
    "100488I": {
        "success": true,
        "runId": 64279681
    },
    "2153C": {
        "success": true,
        "runId": 64454257
    },
    "2160B": {
        "success": true,
        "runId": 64454259
    },
    "103855H": {
        "success": true,
        "runId": 64454260
    },
    "104380F": {
        "success": true,
        "runId": 64454262
    },
    "2150B": {
        "success": true,
        "runId": 64454264
    },
    "2151D": {
        "success": true,
        "runId": 64454267
    },
    "2153D": {
        "success": true,
        "runId": 64454276
    },
    "2160A": {
        "success": true,
        "runId": 64454277
    },
    "2153A": {
        "success": true,
        "runId": 64454278
    },
    "2160D": {
        "success": true,
        "runId": 64454283
    },
    "104679F": {
        "success": true,
        "runId": 64454287
    },
    "2160C": {
        "success": true,
        "runId": 64454289
    },
    "2153B": {
        "success": true,
        "runId": 64454291
    },
    "104679E": {
        "success": true,
        "runId": 64454296
    },
    "103855M": {
        "success": true,
        "runId": 64454298
    },
    "103785H": {
        "success": true,
        "runId": 64715620
    },
    "102409J": {
        "success": true,
        "runId": 64715622
    },
    "2162A": {
        "success": true,
        "runId": 64715625
    },
    "105408G": {
        "success": true,
        "runId": 64715628
    },
    "2154C2": {
        "success": true,
        "runId": 64715631
    },
    "104673A": {
        "success": true,
        "runId": 64715632
    },
    "2162D": {
        "success": true,
        "runId": 64715634
    },
    "2154C1": {
        "success": true,
        "runId": 64715635
    },
    "103855D": {
        "success": true,
        "runId": 64715637
    },
    "105487E": {
        "success": true,
        "runId": 64715638
    },
    "102419D": {
        "success": true,
        "runId": 64715640
    },
    "105129L": {
        "success": true,
        "runId": 64715642
    },
    "2162E": {
        "success": true,
        "runId": 64715645
    },
    "2162F": {
        "success": true,
        "runId": 64715652
    },
    "2162B": {
        "success": true,
        "runId": 64715656
    },
    "2162C": {
        "success": true,
        "runId": 64715660
    },
    "103855E": {
        "success": true,
        "runId": 64715662
    },
    "105487L": {
        "success": true,
        "runId": 64715664
    },
    "2162G": {
        "success": true,
        "runId": 64715666
    },
    "2156C": {
        "success": true,
        "runId": 64908549
    },
    "105582G": {
        "success": true,
        "runId": 64908552
    },
    "104848E": {
        "success": true,
        "runId": 64908554
    },
    "2156F1": {
        "success": true,
        "runId": 64908558
    },
    "2154A": {
        "success": true,
        "runId": 64908561
    },
    "888E": {
        "success": true,
        "runId": 64908565
    },
    "106125E": {
        "success": true,
        "runId": 64908574
    },
    "105582K": {
        "success": true,
        "runId": 64908576
    },
    "2156D": {
        "success": true,
        "runId": 64908577
    },
    "2156A": {
        "success": true,
        "runId": 64908578
    },
    "2154B": {
        "success": true,
        "runId": 64908580
    },
    "741C": {
        "success": true,
        "runId": 64908583
    },
    "2156B": {
        "success": true,
        "runId": 64908590
    },
    "525E": {
        "success": true,
        "runId": 64908593
    },
    "104081I": {
        "success": true,
        "runId": 64908594
    },
    "2154D": {
        "success": true,
        "runId": 64908598
    },
    "750A": {
        "success": true,
        "runId": 65690339
    },
    "103427J": {
        "success": false,
        "error": "No recent submissions found"
    },
    "105613E": {
        "success": false,
        "error": "No recent submissions found"
    },
    "104869B": {
        "success": false,
        "error": "No recent submissions found"
    },
    "2164C": {
        "success": false,
        "error": "No recent submissions found"
    },
    "4C": {
        "success": false,
        "error": "No recent submissions found"
    },
    "2164B": {
        "success": false,
        "error": "No recent submissions found"
    },
    "230B": {
        "success": false,
        "error": "No recent submissions found"
    },
    "25A": {
        "success": false,
        "error": "No recent submissions found"
    },
    "230A": {
        "success": false,
        "error": "No recent submissions found"
    },
    "2169D2": {
        "success": true,
        "runId": 65690376
    },
    "1703A": {
        "success": false,
        "error": "No recent submissions found"
    },
    "2169C": {
        "success": true,
        "runId": 65690385
    },
    "158B": {
        "success": false,
        "error": "No recent submissions found"
    },
    "2167D": {
        "success": false,
        "error": "No recent submissions found"
    },
    "144A": {
        "success": false,
        "error": "No recent submissions found"
    },
    "2166E": {
        "success": true,
        "runId": 65690403
    },
    "104869M": {
        "success": false,
        "error": "No recent submissions found"
    },
    "2167C": {
        "success": false,
        "error": "No recent submissions found"
    },
    "580A": {
        "success": false,
        "error": "No recent submissions found"
    },
    "2167B": {
        "success": false,
        "error": "No recent submissions found"
    },
    "996A": {
        "success": false,
        "error": "No recent submissions found"
    },
    "104873I": {
        "success": false,
        "error": "No recent submissions found"
    },
    "104869J": {
        "success": false,
        "error": "No recent submissions found"
    },
    "977A": {
        "success": false,
        "error": "No recent submissions found"
    },
    "104160F": {
        "success": false,
        "error": "No recent submissions found"
    },
    "2169B": {
        "success": true,
        "runId": 65690427
    },
    "600E": {
        "success": false,
        "error": "No recent submissions found"
    },
    "106139D": {
        "success": false,
        "error": "No recent submissions found"
    },
    "236A": {
        "success": false,
        "error": "No recent submissions found"
    },
    "104160C": {
        "success": false,
        "error": "No recent submissions found"
    },
    "136A": {
        "success": false,
        "error": "No recent submissions found"
    },
    "151A": {
        "success": false,
        "error": "No recent submissions found"
    },
    "131A": {
        "success": false,
        "error": "No recent submissions found"
    },
    "112A": {
        "success": false,
        "error": "No recent submissions found"
    },
    "155A": {
        "success": false,
        "error": "No recent submissions found"
    },
    "2167E": {
        "success": false,
        "error": "No recent submissions found"
    },
    "104869E": {
        "success": false,
        "error": "No recent submissions found"
    },
    "337A": {
        "success": false,
        "error": "No recent submissions found"
    },
    "318A": {
        "success": false,
        "error": "No recent submissions found"
    },
    "1742A": {
        "success": false,
        "error": "No recent submissions found"
    },
    "41A": {
        "success": false,
        "error": "No recent submissions found"
    },
    "104160D": {
        "success": false,
        "error": "No recent submissions found"
    },
    "2168A2": {
        "success": true,
        "runId": 65690451
    },
    "630A": {
        "success": true,
        "runId": 65690452
    },
    "405A": {
        "success": false,
        "error": "No recent submissions found"
    },
    "103427E": {
        "success": false,
        "error": "No recent submissions found"
    },
    "2166C": {
        "success": true,
        "runId": 65690459
    },
    "344A": {
        "success": false,
        "error": "No recent submissions found"
    },
    "208A": {
        "success": false,
        "error": "No recent submissions found"
    },
    "467A": {
        "success": false,
        "error": "No recent submissions found"
    },
    "427A": {
        "success": false,
        "error": "No recent submissions found"
    },
    "104869H": {
        "success": false,
        "error": "No recent submissions found"
    },
    "105901I": {
        "success": false,
        "error": "No recent submissions found"
    },
    "723A": {
        "success": false,
        "error": "No recent submissions found"
    },
    "271A": {
        "success": false,
        "error": "No recent submissions found"
    },
    "443A": {
        "success": false,
        "error": "No recent submissions found"
    },
    "106129F": {
        "success": false,
        "error": "No recent submissions found"
    },
    "160A": {
        "success": false,
        "error": "No recent submissions found"
    },
    "1154A": {
        "success": true,
        "runId": 65690476
    },
    "2164D": {
        "success": false,
        "error": "No recent submissions found"
    },
    "61A": {
        "success": false,
        "error": "No recent submissions found"
    },
    "268A": {
        "success": false,
        "error": "No recent submissions found"
    },
    "122A": {
        "success": false,
        "error": "No recent submissions found"
    },
    "110A": {
        "success": false,
        "error": "No recent submissions found"
    },
    "266B": {
        "success": false,
        "error": "No recent submissions found"
    },
    "104869C": {
        "success": false,
        "error": "No recent submissions found"
    },
    "2166B": {
        "success": true,
        "runId": 65690491
    },
    "2161D": {
        "success": false,
        "error": "No recent submissions found"
    },
    "1352A": {
        "success": false,
        "error": "No recent submissions found"
    },
    "2163B": {
        "success": false,
        "error": "No recent submissions found"
    },
    "105386K": {
        "success": false,
        "error": "No recent submissions found"
    },
    "677A": {
        "success": false,
        "error": "No recent submissions found"
    },
    "2163A": {
        "success": false,
        "error": "No recent submissions found"
    },
    "105901A": {
        "success": false,
        "error": "No recent submissions found"
    },
    "510A": {
        "success": false,
        "error": "No recent submissions found"
    },
    "546A": {
        "success": false,
        "error": "No recent submissions found"
    },
    "200B": {
        "success": false,
        "error": "No recent submissions found"
    },
    "281A": {
        "success": false,
        "error": "No recent submissions found"
    },
    "104160L": {
        "success": false,
        "error": "No recent submissions found"
    },
    "791A": {
        "success": false,
        "error": "No recent submissions found"
    },
    "1030A": {
        "success": false,
        "error": "No recent submissions found"
    },
    "1335A": {
        "success": false,
        "error": "No recent submissions found"
    },
    "116A": {
        "success": false,
        "error": "No recent submissions found"
    },
    "2167F": {
        "success": false,
        "error": "No recent submissions found"
    },
    "469A": {
        "success": false,
        "error": "No recent submissions found"
    },
    "1328A": {
        "success": false,
        "error": "No recent submissions found"
    },
    "705A": {
        "success": false,
        "error": "No recent submissions found"
    },
    "617A": {
        "success": false,
        "error": "No recent submissions found"
    },
    "228A": {
        "success": false,
        "error": "No recent submissions found"
    },
    "104869K": {
        "success": false,
        "error": "No recent submissions found"
    },
    "492B": {
        "success": true,
        "runId": 65690562
    },
    "106139E": {
        "success": false,
        "error": "No recent submissions found"
    },
    "734A": {
        "success": false,
        "error": "No recent submissions found"
    },
    "520A": {
        "success": false,
        "error": "No recent submissions found"
    },
    "2163C": {
        "success": false,
        "error": "No recent submissions found"
    },
    "1A": {
        "success": false,
        "error": "No recent submissions found"
    },
    "2169A": {
        "success": true,
        "runId": 65690579
    },
    "2167A": {
        "success": false,
        "error": "No recent submissions found"
    },
    "381A": {
        "success": true,
        "runId": 65690602
    },
    "118A": {
        "success": false,
        "error": "No recent submissions found"
    },
    "2164A": {
        "success": false,
        "error": "No recent submissions found"
    },
    "103427F": {
        "success": false,
        "error": "No recent submissions found"
    },
    "2166A": {
        "success": true,
        "runId": 65690610
    },
    "133A": {
        "success": false,
        "error": "No recent submissions found"
    },
    "59A": {
        "success": false,
        "error": "No recent submissions found"
    },
    "69A": {
        "success": false,
        "error": "No recent submissions found"
    },
    "96A": {
        "success": false,
        "error": "No recent submissions found"
    },
    "785A": {
        "success": false,
        "error": "No recent submissions found"
    },
    "58A": {
        "success": false,
        "error": "No recent submissions found"
    },
    "2168A1": {
        "success": true,
        "runId": 65690623
    },
    "106139B": {
        "success": false,
        "error": "No recent submissions found"
    },
    "339A": {
        "success": false,
        "error": "No recent submissions found"
    },
    "479A": {
        "success": false,
        "error": "No recent submissions found"
    },
    "141A": {
        "success": false,
        "error": "No recent submissions found"
    },
    "2169D1": {
        "success": true,
        "runId": 65690630
    },
    "486A": {
        "success": false,
        "error": "No recent submissions found"
    },
    "732A": {
        "success": true,
        "runId": 65690634
    },
    "148A": {
        "success": false,
        "error": "No recent submissions found"
    },
    "105901L": {
        "success": false,
        "error": "No recent submissions found"
    },
    "266A": {
        "success": false,
        "error": "No recent submissions found"
    },
    "103427B": {
        "success": false,
        "error": "No recent submissions found"
    },
    "2167G": {
        "success": false,
        "error": "No recent submissions found"
    },
    "104160B": {
        "success": false,
        "error": "No recent submissions found"
    },
    "339B": {
        "success": false,
        "error": "No recent submissions found"
    },
    "1807A": {
        "success": true,
        "runId": 65692614
    },
    "1692A": {
        "success": true,
        "runId": 65692617
    },
    "1899A": {
        "success": true,
        "runId": 65692619
    },
    "1999A": {
        "success": true,
        "runId": 65692623
    },
    "1676A": {
        "success": true,
        "runId": 65692626
    },
    "581A": {
        "success": true,
        "runId": 65692629
    },
    "1475A": {
        "success": true,
        "runId": 65692632
    },
    "189A": {
        "success": true,
        "runId": 65692636
    },
    "706B": {
        "success": true,
        "runId": 65692642
    },
    "1669A": {
        "success": true,
        "runId": 65692646
    }
}